siws/__init__.py
siws/custom_types.py
siws/defs.py
siws/exceptions.py
siws/parsed.py
siws/siws.py
siws/utils.py
siws/grammars/__init__.py
siws/grammars/eip4361.py
siws/grammars/rfc3339.py
siws/grammars/rfc5234.py
siws-0.0.2.dist-info/LICENSE
siws-0.0.2.dist-info/METADATA
siws-0.0.2.dist-info/WHEEL
siws-0.0.2.dist-info/top_level.txt
siws-0.0.2.dist-info/RECORD
