Metadata-Version: 2.1
Name: siws
Version: 0.0.2
Summary: A python adaptation from Sign it with ethereum for Stacks
Home-page: https://github.com/palma9/siws-py
Author: Jesús Palma
Author-email: jpalmalop@gmail.com
Classifier: Programming Language :: Python :: 3
Classifier: License :: OSI Approved :: MIT License
Classifier: Operating System :: OS Independent
License-File: LICENSE
Requires-Dist: pydantic
Requires-Dist: abnf
Requires-Dist: python-dateutil
Requires-Dist: ecdsa
